<?xml version="1.0" encoding="utf-8"?>
<LanguageData>
  <SylvieRace_FirstName>Sylvie</SylvieRace_FirstName>
  <CallSpecialApparelTrader>Call special apparel trader (free)</CallSpecialApparelTrader>
  <Sylvie_ClothingSupplyShipName>Clothing Supply Ship</Sylvie_ClothingSupplyShipName>
  <Sylvie_TraderAlreadyInOrbit>The trader is already in nearby orbit.</Sylvie_TraderAlreadyInOrbit>
  <Sylvie_TraderArrived>A clothing trade ship has entered comm range.</Sylvie_TraderArrived>
  <Sylvie_OfferLabel>A Special Trade Offer</Sylvie_OfferLabel>
  <Sylvie_OfferText>A merchant pulls you aside.\n\nMerchant: "Dear customer, a nobleman went bankrupt recently, and I benefited somewhat from that. But along with it, they also left me some things I don't particularly care for — like this slave."\n\nHe points to a female slave covered in scars. She looks very young, curled up tightly in a corner.\n\nMerchant: "If you don't mind, I could sell this slave to you at quite a low price. She has all her limbs intact and can do plenty of work. Besides, everyone around here knows you've been tending to our wounds all by yourself — consider this repayment for saving my life."\n\nShould you take this girl in?</Sylvie_OfferText>
  <Sylvie_PayAndTakeHer>Pay {0} silver and take her in</Sylvie_PayAndTakeHer>
  <Sylvie_TradeSuccess>Trade successful. Sylvie has joined the colony.</Sylvie_TradeSuccess>
  <Sylvie_NotEnoughSilver>Not enough silver (current: {0})</Sylvie_NotEnoughSilver>
  <Sylvie_Refuse>Refuse</Sylvie_Refuse>
  <SylvieRace_HediffLetterLabel>Sylvie's Health Issue</SylvieRace_HediffLetterLabel>
  <SylvieRace_HediffLetterText>{0} seems to be showing signs of trauma from past experiences. She may need medical attention and care.</SylvieRace_HediffLetterText>
  <SylvieRace_NurseHeal_Label>Emergency Treatment</SylvieRace_NurseHeal_Label>
  <SylvieRace_NurseHeal_Desc>Immediately bandage all untreated wounds, but causes 1 hour of paralysis. 2 hour cooldown.</SylvieRace_NurseHeal_Desc>
  <SylvieRace_NurseHeal_Cooldown>Cooldown remaining: {0}</SylvieRace_NurseHeal_Cooldown>
  <SylvieRace_NurseHeal_NoWounds>{0} has no untreated wounds to heal.</SylvieRace_NurseHeal_NoWounds>
  <SylvieRace_NurseHeal_Success>{0}'s wounds have been bandaged, but she is now paralyzed for 1 hour.</SylvieRace_NurseHeal_Success>
</LanguageData>
